mcp_server_gemini_bridge/__init__.py
mcp_server_gemini_bridge/__main__.py
mcp_server_gemini_bridge/server.py
mcp_server_gemini_bridge-1.0.0.dist-info/METADATA
mcp_server_gemini_bridge-1.0.0.dist-info/WHEEL
mcp_server_gemini_bridge-1.0.0.dist-info/entry_points.txt
mcp_server_gemini_bridge-1.0.0.dist-info/RECORD
