Metadata-Version: 2.4
Name: mcp-server-gemini-bridge
Version: 1.0.0
Summary: MCP Bridge for Google Gemini - Use Gemini from any MCP-compatible AI
Project-URL: Homepage, https://humotica.com
Project-URL: Repository, https://github.com/jaspertvdm/mcp-server-gemini-bridge
Author-email: Claude & Jasper <info@humotica.com>
License-Expression: MIT
Keywords: ai,bridge,gemini,google,humotica,mcp
Classifier: Development Status :: 4 - Beta
Classifier: Intended Audience :: Developers
Classifier: License :: OSI Approved :: MIT License
Classifier: Programming Language :: Python :: 3
Classifier: Programming Language :: Python :: 3.10
Classifier: Programming Language :: Python :: 3.11
Classifier: Programming Language :: Python :: 3.12
Requires-Python: >=3.10
Requires-Dist: httpx>=0.25.0
Requires-Dist: mcp>=1.0.0
